hello/__init__.py
hello/hello.py
salimiana-0.0.1.dist-info/METADATA
salimiana-0.0.1.dist-info/WHEEL
salimiana-0.0.1.dist-info/top_level.txt
salimiana-0.0.1.dist-info/RECORD
